bflower/version/__init__.py
bflower/version/version.py
bflower-1.0.0a35.dist-info/LICENSE
bflower-1.0.0a35.dist-info/METADATA
bflower-1.0.0a35.dist-info/WHEEL
bflower-1.0.0a35.dist-info/entry_points.txt
bflower-1.0.0a35.dist-info/RECORD
