Metadata-Version: 2.1
Name: bflower
Version: 1.0.0a35
Summary: A Python package with a built-in web application
Home-page: https://github.com/BNationsDEV/BFlower
License: MIT
Keywords: nlp,langchain,openai,gpt,gui
Author: Langflow
Author-email: contact@langflow.org
Maintainer: Carlos Coelho
Maintainer-email: carlos@langflow.org
Requires-Python: >=3.10,<3.13
Classifier: License :: OSI Approved :: MIT License
Classifier: Programming Language :: Python :: 3
Classifier: Programming Language :: Python :: 3.10
Classifier: Programming Language :: Python :: 3.11
Classifier: Programming Language :: Python :: 3.12
Provides-Extra: deploy
Provides-Extra: local
Requires-Dist: assemblyai (>=0.23.1,<0.24.0)
Requires-Dist: beautifulsoup4 (>=4.12.2,<5.0.0)
Requires-Dist: bflower-base (>=0.0.43,<0.0.44)
Requires-Dist: boto3 (>=1.34.0,<2.0.0)
Requires-Dist: celery[redis] (>=5.3.6,<6.0.0) ; extra == "deploy"
Requires-Dist: certifi (>=2023.11.17,<2024.0.0)
Requires-Dist: chromadb (>=0.4.24,<0.5.0)
Requires-Dist: cohere (>=5.1.7,<6.0.0)
Requires-Dist: ctransformers (>=0.2.10,<0.3.0) ; extra == "local"
Requires-Dist: dspy-ai (>=2.4.0,<3.0.0)
Requires-Dist: elasticsearch (>=8.12.0,<9.0.0)
Requires-Dist: extract-msg (>=0.47.0,<0.48.0)
Requires-Dist: faiss-cpu (>=1.7.4,<2.0.0)
Requires-Dist: fake-useragent (>=1.4.0,<2.0.0)
Requires-Dist: fastavro (>=1.8.0,<2.0.0)
Requires-Dist: flower (>=2.0.0,<3.0.0) ; extra == "deploy"
Requires-Dist: google-api-python-client (>=2.118.0,<3.0.0)
Requires-Dist: google-search-results (>=2.4.1,<3.0.0)
Requires-Dist: html2text (>=2024.2.26,<2025.0.0)
Requires-Dist: huggingface-hub[inference] (>=0.20.0,<0.21.0)
Requires-Dist: langchain-anthropic (>=0.1.6,<0.2.0)
Requires-Dist: langchain-astradb (>=0.1.0,<0.2.0)
Requires-Dist: langchain-cohere (>=0.1.0rc1,<0.2.0)
Requires-Dist: langchain-google-genai (>=1.0.1,<2.0.0)
Requires-Dist: langchain-google-vertexai (>=1.0.3,<2.0.0)
Requires-Dist: langchain-groq (>=0.1.3,<0.2.0)
Requires-Dist: langchain-mistralai (>=0.1.6,<0.2.0)
Requires-Dist: langchain-openai (>=0.1.1,<0.2.0)
Requires-Dist: langchain-pinecone (>=0.1.0,<0.2.0)
Requires-Dist: langfuse (>=2.9.0,<3.0.0)
Requires-Dist: litellm (>=1.34.22,<2.0.0)
Requires-Dist: llama-cpp-python (>=0.2.0,<0.3.0) ; extra == "local"
Requires-Dist: llama-index (>=0.10.13,<0.11.0)
Requires-Dist: markupsafe (>=2.1.3,<3.0.0)
Requires-Dist: metal-sdk (>=2.5.0,<3.0.0)
Requires-Dist: metaphor-python (>=0.1.11,<0.2.0)
Requires-Dist: nats-py (>=2.7.2,<3.0.0)
Requires-Dist: networkx (>=3.1,<4.0)
Requires-Dist: numexpr (>=2.8.6,<3.0.0)
Requires-Dist: pgvector (>=0.2.3,<0.3.0)
Requires-Dist: pinecone-client (>=3.0.3,<4.0.0)
Requires-Dist: psycopg (>=3.1.9,<4.0.0)
Requires-Dist: psycopg-binary (>=3.1.9,<4.0.0)
Requires-Dist: psycopg2-binary (>=2.9.6,<3.0.0)
Requires-Dist: pyarrow (>=14.0.0,<15.0.0)
Requires-Dist: pyautogen (>=0.2.0,<0.3.0)
Requires-Dist: pymongo (>=4.6.0,<5.0.0)
Requires-Dist: pysrt (>=1.1.2,<2.0.0)
Requires-Dist: pytube (>=15.0.0,<16.0.0)
Requires-Dist: pywin32 (>=306,<307) ; sys_platform == "win32"
Requires-Dist: qdrant-client (>=1.7.0,<2.0.0)
Requires-Dist: qianfan (==0.3.5)
Requires-Dist: redis (>=5.0.1,<6.0.0) ; extra == "deploy"
Requires-Dist: sentence-transformers (>=2.3.1,<3.0.0) ; extra == "local"
Requires-Dist: supabase (>=2.3.0,<3.0.0)
Requires-Dist: types-cachetools (>=5.3.0.5,<6.0.0.0)
Requires-Dist: weaviate-client
Requires-Dist: wikipedia (>=1.4.0,<2.0.0)
Requires-Dist: zep-python (>=2.0.0rc5,<3.0.0)
Project-URL: Documentation, https://docs.langflow.org
Project-URL: Repository, https://github.com/BNationsDEV/BFlower
